all_repos_envvar/__init__.py
all_repos_envvar/mixin.py
all_repos_envvar/push.py
all_repos_envvar/py.typed
all_repos_envvar/source.py
all_repos_envvar-1.4.0.dist-info/licenses/LICENSE
all_repos_envvar-1.4.0.dist-info/METADATA
all_repos_envvar-1.4.0.dist-info/WHEEL
all_repos_envvar-1.4.0.dist-info/top_level.txt
all_repos_envvar-1.4.0.dist-info/RECORD
