Metadata-Version: 2.4
Name: all-repos-envvar
Version: 1.4.0
Summary: An all-repos extension to read values from environment variables.
Author-email: Bruno Alla <alla.brunoo@gmail.com>
License-Expression: MIT
Project-URL: Bug Tracker, https://github.com/browniebroke/all-repos-envvar/issues
Project-URL: Changelog, https://all-repos-envvar.readthedocs.io/changelog.html
Project-URL: documentation, https://all-repos-envvar.readthedocs.io
Project-URL: Mastodon, https://fosstodon.org/@browniebroke
Project-URL: repository, https://github.com/browniebroke/all-repos-envvar
Project-URL: Twitter, https://twitter.com/_BrunoAlla
Classifier: Development Status :: 2 - Pre-Alpha
Classifier: Intended Audience :: Developers
Classifier: Natural Language :: English
Classifier: Operating System :: OS Independent
Classifier: Programming Language :: Python :: 3 :: Only
Classifier: Programming Language :: Python :: 3.10
Classifier: Programming Language :: Python :: 3.11
Classifier: Programming Language :: Python :: 3.12
Classifier: Programming Language :: Python :: 3.13
Classifier: Programming Language :: Python :: 3.14
Classifier: Topic :: Software Development :: Libraries
Requires-Python: >=3.10
License-File: LICENSE
Requires-Dist: all-repos>=1
Requires-Dist: environs>=10
Dynamic: license-file
